<?xml version="1.0" encoding="UTF-8"?>
<DocSetNodes version="1.0">
  <TOC>
    <Node>
      <Name>Root</Name>
      <Path>index.html</Path>
      <Subnodes>
       <Node>
        <Name>README</Name>
        <Path>md__r_e_a_d_m_e.html</Path>
       </Node>
       <Node>
        <Name>Classes</Name>
        <Path></Path>
        <Subnodes>
         <Node>
          <Name>Class List</Name>
          <Path>annotated.html</Path>
          <Subnodes>
           <Node>
            <Name>Card</Name>
            <Path>interface_card.html</Path>
            <Subnodes>
             <Node>
              <Name>match:</Name>
              <Path>interface_card.html</Path>
              <Anchor>a57f272caea14ec15f478d6994113ba45</Anchor>
             </Node>
             <Node>
              <Name>contents</Name>
              <Path>interface_card.html</Path>
              <Anchor>a0e6c994515c10dd93e64fe3be918e435</Anchor>
             </Node>
             <Node>
              <Name>faceUp</Name>
              <Path>interface_card.html</Path>
              <Anchor>a52d18330127b279f9f9bb2724da7fbe9</Anchor>
             </Node>
             <Node>
              <Name>unpleyable</Name>
              <Path>interface_card.html</Path>
              <Anchor>ac8b8a7d18701dcfd2979620b0a953fa3</Anchor>
             </Node>
            </Subnodes>
           </Node>
           <Node>
            <Name>CardGameAppDelegate</Name>
            <Path>interface_card_game_app_delegate.html</Path>
            <Subnodes>
             <Node>
              <Name>window</Name>
              <Path>interface_card_game_app_delegate.html</Path>
              <Anchor>a306848ae86613bf9c6f0e48ba588cc5a</Anchor>
             </Node>
            </Subnodes>
           </Node>
           <Node>
            <Name>CardGameViewController</Name>
            <Path>interface_card_game_view_controller.html</Path>
           </Node>
           <Node>
            <Name>CardGameViewController()</Name>
            <Path>category_card_game_view_controller_07_08.html</Path>
            <Subnodes>
             <Node>
              <Name>IBOutletCollection</Name>
              <Path>category_card_game_view_controller_07_08.html</Path>
              <Anchor>a23f8506ae2b6e846479e08555b78fe08</Anchor>
             </Node>
             <Node>
              <Name>chooseGame</Name>
              <Path>category_card_game_view_controller_07_08.html</Path>
              <Anchor>a183341b3e34ef7332fe5de00ba58b77f</Anchor>
             </Node>
             <Node>
              <Name>flipCount</Name>
              <Path>category_card_game_view_controller_07_08.html</Path>
              <Anchor>a53a35dc2ae87098d7f35f2a9720d9900</Anchor>
             </Node>
             <Node>
              <Name>flipedCard</Name>
              <Path>category_card_game_view_controller_07_08.html</Path>
              <Anchor>a41dba9ad5db3f721b3bc62121098d03e</Anchor>
             </Node>
             <Node>
              <Name>flipsLabel</Name>
              <Path>category_card_game_view_controller_07_08.html</Path>
              <Anchor>a70e32358c1ab6c3aa1780be62bef3480</Anchor>
             </Node>
             <Node>
              <Name>game</Name>
              <Path>category_card_game_view_controller_07_08.html</Path>
              <Anchor>a956eedfeffcb61d695412ed9d9499877</Anchor>
             </Node>
             <Node>
              <Name>gameSelector</Name>
              <Path>category_card_game_view_controller_07_08.html</Path>
              <Anchor>ab2e690e4e87bc4af55c347eee2df8a04</Anchor>
             </Node>
             <Node>
              <Name>gameStateString</Name>
              <Path>category_card_game_view_controller_07_08.html</Path>
              <Anchor>a5f450b7a8a2294c3643e700d2af61585</Anchor>
             </Node>
             <Node>
              <Name>machedCards</Name>
              <Path>category_card_game_view_controller_07_08.html</Path>
              <Anchor>a4224e31f36861d33f4fe3de0e2335e35</Anchor>
             </Node>
             <Node>
              <Name>machedCardsLabel</Name>
              <Path>category_card_game_view_controller_07_08.html</Path>
              <Anchor>abe4ed7dab8d9be382c723df3f05dc581</Anchor>
             </Node>
             <Node>
              <Name>scoreLabel</Name>
              <Path>category_card_game_view_controller_07_08.html</Path>
              <Anchor>a1288bd6ba439a4fe7d33944ad416774d</Anchor>
             </Node>
            </Subnodes>
           </Node>
           <Node>
            <Name>CardMatchingGame</Name>
            <Path>interface_card_matching_game.html</Path>
            <Subnodes>
             <Node>
              <Name>cardAtIndex:</Name>
              <Path>interface_card_matching_game.html</Path>
              <Anchor>ae678d55b9b2fa8415ccde4415011c431</Anchor>
             </Node>
             <Node>
              <Name>flipCardAtIndex:</Name>
              <Path>interface_card_matching_game.html</Path>
              <Anchor>ab1a126ff961f3fe2690d51379bdff756</Anchor>
             </Node>
             <Node>
              <Name>initWithCardCount:usingDeck:</Name>
              <Path>interface_card_matching_game.html</Path>
              <Anchor>a4e987a716e3201cdf28288b8ec31ccb3</Anchor>
             </Node>
             <Node>
              <Name>twoCardGame:</Name>
              <Path>interface_card_matching_game.html</Path>
              <Anchor>a4121dc0cb4f8eeaef69b4fe01568b838</Anchor>
             </Node>
             <Node>
              <Name>matchingCardGameMode</Name>
              <Path>interface_card_matching_game.html</Path>
              <Anchor>ad4647526b48000f5d14d2cfe71a2cfee</Anchor>
             </Node>
             <Node>
              <Name>score</Name>
              <Path>interface_card_matching_game.html</Path>
              <Anchor>a3d18fe0bed51d95f0fe0af34bed164fb</Anchor>
             </Node>
            </Subnodes>
           </Node>
           <Node>
            <Name>CardMatchingGame()</Name>
            <Path>category_card_matching_game_07_08.html</Path>
            <Subnodes>
             <Node>
              <Name>cards</Name>
              <Path>category_card_matching_game_07_08.html</Path>
              <Anchor>a9c9dbb6744f10f10d240e9cf7815a75e</Anchor>
             </Node>
             <Node>
              <Name>matchedCardAttribute</Name>
              <Path>category_card_matching_game_07_08.html</Path>
              <Anchor>aab609fbd5868e9fd6d9d5eb3b858bffe</Anchor>
             </Node>
             <Node>
              <Name>matchedCards</Name>
              <Path>category_card_matching_game_07_08.html</Path>
              <Anchor>a248b47b8772efdb1124525598fd0646b</Anchor>
             </Node>
             <Node>
              <Name>score</Name>
              <Path>category_card_matching_game_07_08.html</Path>
              <Anchor>a333427cac9f1279aef48c62236b684e8</Anchor>
             </Node>
            </Subnodes>
           </Node>
           <Node>
            <Name>Deck</Name>
            <Path>interface_deck.html</Path>
            <Subnodes>
             <Node>
              <Name>addCard:atTop:</Name>
              <Path>interface_deck.html</Path>
              <Anchor>a2a2a6e34c420494bf79949a619a38a42</Anchor>
             </Node>
             <Node>
              <Name>drawRandomCard</Name>
              <Path>interface_deck.html</Path>
              <Anchor>a4e700b33095cd278339e9176442e3c0e</Anchor>
             </Node>
            </Subnodes>
           </Node>
           <Node>
            <Name>Deck()</Name>
            <Path>category_deck_07_08.html</Path>
            <Subnodes>
             <Node>
              <Name>cards</Name>
              <Path>category_deck_07_08.html</Path>
              <Anchor>afe9be65c5a389787493e8cfdce431ac6</Anchor>
             </Node>
            </Subnodes>
           </Node>
           <Node>
            <Name>PlayingCard</Name>
            <Path>interface_playing_card.html</Path>
            <Subnodes>
             <Node>
              <Name>matchedAttribute</Name>
              <Path>interface_playing_card.html</Path>
              <Anchor>abf81fb99ec0ee06750cec7bf260023fc</Anchor>
             </Node>
             <Node>
              <Name>maxRank</Name>
              <Path>interface_playing_card.html</Path>
              <Anchor>aba2d34b27f0277de77bfcbddb2194097</Anchor>
             </Node>
             <Node>
              <Name>validSuits</Name>
              <Path>interface_playing_card.html</Path>
              <Anchor>a99ac3b30dc0c4ebd3cb764bed4a9d086</Anchor>
             </Node>
             <Node>
              <Name>verfyMatch:</Name>
              <Path>interface_playing_card.html</Path>
              <Anchor>aa9418a8b1ff3392187bd52bbc2958599</Anchor>
             </Node>
             <Node>
              <Name>matchedCardAttribute</Name>
              <Path>interface_playing_card.html</Path>
              <Anchor>a0abea59afda1d6d47e96b45685c24a3f</Anchor>
             </Node>
             <Node>
              <Name>rank</Name>
              <Path>interface_playing_card.html</Path>
              <Anchor>a6b113dc314b08d58d8b4ed7775a6695a</Anchor>
             </Node>
             <Node>
              <Name>suit</Name>
              <Path>interface_playing_card.html</Path>
              <Anchor>a67ae30190b0facc603bdfc4ae8b51fcb</Anchor>
             </Node>
            </Subnodes>
           </Node>
           <Node>
            <Name>PlayingCardDeck</Name>
            <Path>interface_playing_card_deck.html</Path>
           </Node>
          </Subnodes>
         </Node>
         <Node>
          <Name>Class Index</Name>
          <Path>classes.html</Path>
         </Node>
         <Node>
          <Name>Class Hierarchy</Name>
          <Path>hierarchy.html</Path>
          <Subnodes>
           <Node>
            <Name>CardGameViewController()</Name>
            <Path>category_card_game_view_controller_07_08.html</Path>
           </Node>
           <Node>
            <Name>CardMatchingGame()</Name>
            <Path>category_card_matching_game_07_08.html</Path>
           </Node>
           <Node>
            <Name>Deck()</Name>
            <Path>category_deck_07_08.html</Path>
           </Node>
           <Node>
            <Name>NSObject</Name>
            <Path></Path>
            <Subnodes>
             <Node>
              <Name>Card</Name>
              <Path>interface_card.html</Path>
              <Subnodes>
               <Node>
                <Name>PlayingCard</Name>
                <Path>interface_playing_card.html</Path>
               </Node>
              </Subnodes>
             </Node>
             <Node>
              <Name>CardMatchingGame</Name>
              <Path>interface_card_matching_game.html</Path>
             </Node>
             <Node>
              <Name>Deck</Name>
              <Path>interface_deck.html</Path>
              <Subnodes>
               <Node>
                <Name>PlayingCardDeck</Name>
                <Path>interface_playing_card_deck.html</Path>
               </Node>
              </Subnodes>
             </Node>
            </Subnodes>
           </Node>
           <Node>
            <Name>&lt;UIApplicationDelegate&gt;</Name>
            <Path></Path>
            <Subnodes>
             <Node>
              <Name>CardGameAppDelegate</Name>
              <Path>interface_card_game_app_delegate.html</Path>
             </Node>
            </Subnodes>
           </Node>
           <Node>
            <Name>UIResponder</Name>
            <Path></Path>
            <Subnodes>
             <Node>
              <Name>CardGameAppDelegate</Name>
              <Path>interface_card_game_app_delegate.html</Path>
             </Node>
            </Subnodes>
           </Node>
           <Node>
            <Name>UIViewController</Name>
            <Path></Path>
            <Subnodes>
             <Node>
              <Name>CardGameViewController</Name>
              <Path>interface_card_game_view_controller.html</Path>
             </Node>
            </Subnodes>
           </Node>
          </Subnodes>
         </Node>
         <Node>
          <Name>Class Members</Name>
          <Path>functions.html</Path>
          <Subnodes>
           <Node>
            <Name>All</Name>
            <Path>functions.html</Path>
           </Node>
           <Node>
            <Name>Functions</Name>
            <Path>functions_func.html</Path>
           </Node>
           <Node>
            <Name>Properties</Name>
            <Path>functions_prop.html</Path>
           </Node>
          </Subnodes>
         </Node>
        </Subnodes>
       </Node>
       <Node>
        <Name>Files</Name>
        <Path></Path>
        <Subnodes>
         <Node>
          <Name>File List</Name>
          <Path>files.html</Path>
          <Subnodes>
           <Node>
            <Name>Matchismo</Name>
            <Path>dir_3989fe30aa95242b6fd13d843c3bc73f.html</Path>
            <Subnodes>
             <Node>
              <Name>Model</Name>
              <Path>dir_4e905a047f1b81c8d06c8e0b6c17acd3.html</Path>
              <Subnodes>
               <Node>
                <Name>Card.h</Name>
                <Path>_card_8h.html</Path>
                <Subnodes>
                 <Node>
                  <Name>Card</Name>
                  <Path>interface_card.html</Path>
                  <Subnodes>
                   <Node>
                    <Name>match:</Name>
                    <Path>interface_card.html</Path>
                    <Anchor>a57f272caea14ec15f478d6994113ba45</Anchor>
                   </Node>
                   <Node>
                    <Name>contents</Name>
                    <Path>interface_card.html</Path>
                    <Anchor>a0e6c994515c10dd93e64fe3be918e435</Anchor>
                   </Node>
                   <Node>
                    <Name>faceUp</Name>
                    <Path>interface_card.html</Path>
                    <Anchor>a52d18330127b279f9f9bb2724da7fbe9</Anchor>
                   </Node>
                   <Node>
                    <Name>unpleyable</Name>
                    <Path>interface_card.html</Path>
                    <Anchor>ac8b8a7d18701dcfd2979620b0a953fa3</Anchor>
                   </Node>
                  </Subnodes>
                 </Node>
                </Subnodes>
               </Node>
               <Node>
                <Name>Card.m</Name>
                <Path>_card_8m.html</Path>
               </Node>
               <Node>
                <Name>CardMatchingGame.h</Name>
                <Path>_card_matching_game_8h.html</Path>
                <Subnodes>
                 <Node>
                  <Name>CardMatchingGame</Name>
                  <Path>interface_card_matching_game.html</Path>
                  <Subnodes>
                   <Node>
                    <Name>cardAtIndex:</Name>
                    <Path>interface_card_matching_game.html</Path>
                    <Anchor>ae678d55b9b2fa8415ccde4415011c431</Anchor>
                   </Node>
                   <Node>
                    <Name>flipCardAtIndex:</Name>
                    <Path>interface_card_matching_game.html</Path>
                    <Anchor>ab1a126ff961f3fe2690d51379bdff756</Anchor>
                   </Node>
                   <Node>
                    <Name>initWithCardCount:usingDeck:</Name>
                    <Path>interface_card_matching_game.html</Path>
                    <Anchor>a4e987a716e3201cdf28288b8ec31ccb3</Anchor>
                   </Node>
                   <Node>
                    <Name>twoCardGame:</Name>
                    <Path>interface_card_matching_game.html</Path>
                    <Anchor>a4121dc0cb4f8eeaef69b4fe01568b838</Anchor>
                   </Node>
                   <Node>
                    <Name>matchingCardGameMode</Name>
                    <Path>interface_card_matching_game.html</Path>
                    <Anchor>ad4647526b48000f5d14d2cfe71a2cfee</Anchor>
                   </Node>
                   <Node>
                    <Name>score</Name>
                    <Path>interface_card_matching_game.html</Path>
                    <Anchor>a3d18fe0bed51d95f0fe0af34bed164fb</Anchor>
                   </Node>
                  </Subnodes>
                 </Node>
                </Subnodes>
               </Node>
               <Node>
                <Name>CardMatchingGame.m</Name>
                <Path>_card_matching_game_8m.html</Path>
                <Subnodes>
                 <Node>
                  <Name>CardMatchingGame()</Name>
                  <Path>category_card_matching_game_07_08.html</Path>
                  <Subnodes>
                   <Node>
                    <Name>cards</Name>
                    <Path>category_card_matching_game_07_08.html</Path>
                    <Anchor>a9c9dbb6744f10f10d240e9cf7815a75e</Anchor>
                   </Node>
                   <Node>
                    <Name>matchedCardAttribute</Name>
                    <Path>category_card_matching_game_07_08.html</Path>
                    <Anchor>aab609fbd5868e9fd6d9d5eb3b858bffe</Anchor>
                   </Node>
                   <Node>
                    <Name>matchedCards</Name>
                    <Path>category_card_matching_game_07_08.html</Path>
                    <Anchor>a248b47b8772efdb1124525598fd0646b</Anchor>
                   </Node>
                   <Node>
                    <Name>score</Name>
                    <Path>category_card_matching_game_07_08.html</Path>
                    <Anchor>a333427cac9f1279aef48c62236b684e8</Anchor>
                   </Node>
                  </Subnodes>
                 </Node>
                 <Node>
                  <Name>FLIP_COST</Name>
                  <Path>_card_matching_game_8m.html</Path>
                  <Anchor>a33e9642c178ce2f1acb6397752373340</Anchor>
                 </Node>
                 <Node>
                  <Name>MATCH_BONUS</Name>
                  <Path>_card_matching_game_8m.html</Path>
                  <Anchor>a1893b7b00922d4ae5d69246413737e48</Anchor>
                 </Node>
                 <Node>
                  <Name>MISMATCH_PENALTY</Name>
                  <Path>_card_matching_game_8m.html</Path>
                  <Anchor>ae7482b0556311e796f2f99142b445f69</Anchor>
                 </Node>
                </Subnodes>
               </Node>
               <Node>
                <Name>Deck.h</Name>
                <Path>_deck_8h.html</Path>
                <Subnodes>
                 <Node>
                  <Name>Deck</Name>
                  <Path>interface_deck.html</Path>
                  <Subnodes>
                   <Node>
                    <Name>addCard:atTop:</Name>
                    <Path>interface_deck.html</Path>
                    <Anchor>a2a2a6e34c420494bf79949a619a38a42</Anchor>
                   </Node>
                   <Node>
                    <Name>drawRandomCard</Name>
                    <Path>interface_deck.html</Path>
                    <Anchor>a4e700b33095cd278339e9176442e3c0e</Anchor>
                   </Node>
                  </Subnodes>
                 </Node>
                </Subnodes>
               </Node>
               <Node>
                <Name>Deck.m</Name>
                <Path>_deck_8m.html</Path>
                <Subnodes>
                 <Node>
                  <Name>Deck()</Name>
                  <Path>category_deck_07_08.html</Path>
                  <Subnodes>
                   <Node>
                    <Name>cards</Name>
                    <Path>category_deck_07_08.html</Path>
                    <Anchor>afe9be65c5a389787493e8cfdce431ac6</Anchor>
                   </Node>
                  </Subnodes>
                 </Node>
                </Subnodes>
               </Node>
               <Node>
                <Name>PlayingCard.h</Name>
                <Path>_playing_card_8h.html</Path>
                <Subnodes>
                 <Node>
                  <Name>PlayingCard</Name>
                  <Path>interface_playing_card.html</Path>
                  <Subnodes>
                   <Node>
                    <Name>matchedAttribute</Name>
                    <Path>interface_playing_card.html</Path>
                    <Anchor>abf81fb99ec0ee06750cec7bf260023fc</Anchor>
                   </Node>
                   <Node>
                    <Name>maxRank</Name>
                    <Path>interface_playing_card.html</Path>
                    <Anchor>aba2d34b27f0277de77bfcbddb2194097</Anchor>
                   </Node>
                   <Node>
                    <Name>validSuits</Name>
                    <Path>interface_playing_card.html</Path>
                    <Anchor>a99ac3b30dc0c4ebd3cb764bed4a9d086</Anchor>
                   </Node>
                   <Node>
                    <Name>verfyMatch:</Name>
                    <Path>interface_playing_card.html</Path>
                    <Anchor>aa9418a8b1ff3392187bd52bbc2958599</Anchor>
                   </Node>
                   <Node>
                    <Name>matchedCardAttribute</Name>
                    <Path>interface_playing_card.html</Path>
                    <Anchor>a0abea59afda1d6d47e96b45685c24a3f</Anchor>
                   </Node>
                   <Node>
                    <Name>rank</Name>
                    <Path>interface_playing_card.html</Path>
                    <Anchor>a6b113dc314b08d58d8b4ed7775a6695a</Anchor>
                   </Node>
                   <Node>
                    <Name>suit</Name>
                    <Path>interface_playing_card.html</Path>
                    <Anchor>a67ae30190b0facc603bdfc4ae8b51fcb</Anchor>
                   </Node>
                  </Subnodes>
                 </Node>
                </Subnodes>
               </Node>
               <Node>
                <Name>PlayingCard.m</Name>
                <Path>_playing_card_8m.html</Path>
               </Node>
               <Node>
                <Name>PlayingCardDeck.h</Name>
                <Path>_playing_card_deck_8h.html</Path>
                <Subnodes>
                 <Node>
                  <Name>PlayingCardDeck</Name>
                  <Path>interface_playing_card_deck.html</Path>
                 </Node>
                </Subnodes>
               </Node>
               <Node>
                <Name>PlayingCardDeck.m</Name>
                <Path>_playing_card_deck_8m.html</Path>
               </Node>
              </Subnodes>
             </Node>
             <Node>
              <Name>CardGameAppDelegate.h</Name>
              <Path>_card_game_app_delegate_8h.html</Path>
              <Subnodes>
               <Node>
                <Name>CardGameAppDelegate</Name>
                <Path>interface_card_game_app_delegate.html</Path>
                <Subnodes>
                 <Node>
                  <Name>window</Name>
                  <Path>interface_card_game_app_delegate.html</Path>
                  <Anchor>a306848ae86613bf9c6f0e48ba588cc5a</Anchor>
                 </Node>
                </Subnodes>
               </Node>
              </Subnodes>
             </Node>
             <Node>
              <Name>CardGameAppDelegate.m</Name>
              <Path>_card_game_app_delegate_8m.html</Path>
             </Node>
             <Node>
              <Name>CardGameViewController.h</Name>
              <Path>_card_game_view_controller_8h.html</Path>
              <Subnodes>
               <Node>
                <Name>CardGameViewController</Name>
                <Path>interface_card_game_view_controller.html</Path>
               </Node>
              </Subnodes>
             </Node>
             <Node>
              <Name>CardGameViewController.m</Name>
              <Path>_card_game_view_controller_8m.html</Path>
              <Subnodes>
               <Node>
                <Name>CardGameViewController()</Name>
                <Path>category_card_game_view_controller_07_08.html</Path>
                <Subnodes>
                 <Node>
                  <Name>IBOutletCollection</Name>
                  <Path>category_card_game_view_controller_07_08.html</Path>
                  <Anchor>a23f8506ae2b6e846479e08555b78fe08</Anchor>
                 </Node>
                 <Node>
                  <Name>chooseGame</Name>
                  <Path>category_card_game_view_controller_07_08.html</Path>
                  <Anchor>a183341b3e34ef7332fe5de00ba58b77f</Anchor>
                 </Node>
                 <Node>
                  <Name>flipCount</Name>
                  <Path>category_card_game_view_controller_07_08.html</Path>
                  <Anchor>a53a35dc2ae87098d7f35f2a9720d9900</Anchor>
                 </Node>
                 <Node>
                  <Name>flipedCard</Name>
                  <Path>category_card_game_view_controller_07_08.html</Path>
                  <Anchor>a41dba9ad5db3f721b3bc62121098d03e</Anchor>
                 </Node>
                 <Node>
                  <Name>flipsLabel</Name>
                  <Path>category_card_game_view_controller_07_08.html</Path>
                  <Anchor>a70e32358c1ab6c3aa1780be62bef3480</Anchor>
                 </Node>
                 <Node>
                  <Name>game</Name>
                  <Path>category_card_game_view_controller_07_08.html</Path>
                  <Anchor>a956eedfeffcb61d695412ed9d9499877</Anchor>
                 </Node>
                 <Node>
                  <Name>gameSelector</Name>
                  <Path>category_card_game_view_controller_07_08.html</Path>
                  <Anchor>ab2e690e4e87bc4af55c347eee2df8a04</Anchor>
                 </Node>
                 <Node>
                  <Name>gameStateString</Name>
                  <Path>category_card_game_view_controller_07_08.html</Path>
                  <Anchor>a5f450b7a8a2294c3643e700d2af61585</Anchor>
                 </Node>
                 <Node>
                  <Name>machedCards</Name>
                  <Path>category_card_game_view_controller_07_08.html</Path>
                  <Anchor>a4224e31f36861d33f4fe3de0e2335e35</Anchor>
                 </Node>
                 <Node>
                  <Name>machedCardsLabel</Name>
                  <Path>category_card_game_view_controller_07_08.html</Path>
                  <Anchor>abe4ed7dab8d9be382c723df3f05dc581</Anchor>
                 </Node>
                 <Node>
                  <Name>scoreLabel</Name>
                  <Path>category_card_game_view_controller_07_08.html</Path>
                  <Anchor>a1288bd6ba439a4fe7d33944ad416774d</Anchor>
                 </Node>
                </Subnodes>
               </Node>
               <Node>
                <Name>THREE_CARD_MODE</Name>
                <Path>_card_game_view_controller_8m.html</Path>
                <Anchor>ab5e6cfc5c4df3f46a1d4fd6aca029c11</Anchor>
               </Node>
               <Node>
                <Name>TWO_CARD_MODE</Name>
                <Path>_card_game_view_controller_8m.html</Path>
                <Anchor>a02cc8ea7c765d68655c4c321af9f8df3</Anchor>
               </Node>
              </Subnodes>
             </Node>
             <Node>
              <Name>main.m</Name>
              <Path>main_8m.html</Path>
              <Subnodes>
               <Node>
                <Name>main</Name>
                <Path>main_8m.html</Path>
                <Anchor>a0ddf1224851353fc92bfbff6f499fa97</Anchor>
               </Node>
              </Subnodes>
             </Node>
            </Subnodes>
           </Node>
          </Subnodes>
         </Node>
         <Node>
          <Name>File Members</Name>
          <Path>globals.html</Path>
          <Subnodes>
           <Node>
            <Name>All</Name>
            <Path>globals.html</Path>
           </Node>
           <Node>
            <Name>Functions</Name>
            <Path>globals_func.html</Path>
           </Node>
           <Node>
            <Name>Macros</Name>
            <Path>globals_defs.html</Path>
           </Node>
          </Subnodes>
         </Node>
        </Subnodes>
       </Node>
      </Subnodes>
    </Node>
  </TOC>
</DocSetNodes>
